robertcommon/__init__.py
robertcommon/basic/__init__.py
robertcommon/basic/cache/__init__.py
robertcommon/basic/cache/utils.py
robertcommon/basic/cls/__init__.py
robertcommon/basic/cls/utils.py
robertcommon/basic/data/__init__.py
robertcommon/basic/data/conversion.py
robertcommon/basic/data/crc16.py
robertcommon/basic/data/datatuple.py
robertcommon/basic/data/nametuple.py
robertcommon/basic/data/type.py
robertcommon/basic/data/utils.py
robertcommon/basic/dt/__init__.py
robertcommon/basic/dt/utils.py
robertcommon/basic/encrypt/__init__.py
robertcommon/basic/encrypt/md5.py
robertcommon/basic/encrypt/rsa.py
robertcommon/basic/error/__init__.py
robertcommon/basic/error/utils.py
robertcommon/basic/log/__init__.py
robertcommon/basic/log/utils.py
robertcommon/basic/os/__init__.py
robertcommon/basic/os/file.py
robertcommon/basic/os/path.py
robertcommon/basic/process/__init__.py
robertcommon/basic/process/utils.py
robertcommon/basic/profile/__init__.py
robertcommon/basic/profile/utils.py
robertcommon/basic/re/__init__.py
robertcommon/basic/re/utils.py
robertcommon/basic/safetext/__init__.py
robertcommon/basic/safetext/converter.py
robertcommon/basic/safetext/funcs.py
robertcommon/basic/sugar/__init__.py
robertcommon/basic/sugar/funcs.py
robertcommon/basic/validation/__init__.py
robertcommon/basic/validation/input.py
robertcommon/system/__init__.py
robertcommon/system/driver/__init__.py
robertcommon/system/driver/agent.py
robertcommon/system/driver/base.py
robertcommon/system/driver/obix.py
robertcommon/system/io/__init__.py
robertcommon/system/io/email.py
robertcommon/system/io/file.py
robertcommon/system/io/ftp.py
robertcommon/system/io/http.py
robertcommon/system/io/ini.py
robertcommon/system/io/oss.py
robertcommon/system/io/rabitmq.py
robertcommon/system/io/redis.py
robertcommon/system/io/redis_cache.py
robertcommon/system/io/response.py
robertcommon/system/io/socket.py
robertcommon/system/io/sqlalche.py
robertcommon/system/task/__init__.py
RobertCommon-0.1.4.dist-info/LICENSE
RobertCommon-0.1.4.dist-info/METADATA
RobertCommon-0.1.4.dist-info/WHEEL
RobertCommon-0.1.4.dist-info/top_level.txt
RobertCommon-0.1.4.dist-info/RECORD
